{"nodes": [{"id": "e_ailearningpath_ai_learning_frontend_frontend_src_components_offlinebanner_jsx", "label": "OfflineBanner.jsx", "file_type": "code", "source_file": "E:\\AILearningPath\\ai-learning-frontend\\frontend\\src\\components\\OfflineBanner.jsx", "source_location": "L1"}, {"id": "offlinebanner_offlinebanner", "label": "OfflineBanner()", "file_type": "code", "source_file": "E:\\AILearningPath\\ai-learning-frontend\\frontend\\src\\components\\OfflineBanner.jsx", "source_location": "L3"}], "edges": [{"source": "e_ailearningpath_ai_learning_frontend_frontend_src_components_offlinebanner_jsx", "target": "react", "relation": "imports_from", "confidence": "EXTRACTED", "source_file": "E:\\AILearningPath\\ai-learning-frontend\\frontend\\src\\components\\OfflineBanner.jsx", "source_location": "L1", "weight": 1.0}, {"source": "e_ailearningpath_ai_learning_frontend_frontend_src_components_offlinebanner_jsx", "target": "offlinebanner_offlinebanner", "relation": "contains", "confidence": "EXTRACTED", "source_file": "E:\\AILearningPath\\ai-learning-frontend\\frontend\\src\\components\\OfflineBanner.jsx", "source_location": "L3", "weight": 1.0}], "raw_calls": [{"caller_nid": "offlinebanner_offlinebanner", "callee": "useState", "source_file": "E:\\AILearningPath\\ai-learning-frontend\\frontend\\src\\components\\OfflineBanner.jsx", "source_location": "L4"}, {"caller_nid": "offlinebanner_offlinebanner", "callee": "useEffect", "source_file": "E:\\AILearningPath\\ai-learning-frontend\\frontend\\src\\components\\OfflineBanner.jsx", "source_location": "L6"}]}