{"nodes": [{"id": "e_ailearningpath_ai_learning_frontend_frontend_src_pages_lessons_jsx", "label": "Lessons.jsx", "file_type": "code", "source_file": "E:\\AILearningPath\\ai-learning-frontend\\frontend\\src\\pages\\Lessons.jsx", "source_location": "L1"}, {"id": "lessons_ncertsubject", "label": "ncertSubject()", "file_type": "code", "source_file": "E:\\AILearningPath\\ai-learning-frontend\\frontend\\src\\pages\\Lessons.jsx", "source_location": "L23"}, {"id": "lessons_subjectbar", "label": "SubjectBar()", "file_type": "code", "source_file": "E:\\AILearningPath\\ai-learning-frontend\\frontend\\src\\pages\\Lessons.jsx", "source_location": "L26"}, {"id": "lessons_sciencesubbar", "label": "ScienceSubBar()", "file_type": "code", "source_file": "E:\\AILearningPath\\ai-learning-frontend\\frontend\\src\\pages\\Lessons.jsx", "source_location": "L47"}, {"id": "lessons_lessons", "label": "Lessons()", "file_type": "code", "source_file": "E:\\AILearningPath\\ai-learning-frontend\\frontend\\src\\pages\\Lessons.jsx", "source_location": "L128"}], "edges": [{"source": "e_ailearningpath_ai_learning_frontend_frontend_src_pages_lessons_jsx", "target": "react", "relation": "imports_from", "confidence": "EXTRACTED", "source_file": "E:\\AILearningPath\\ai-learning-frontend\\frontend\\src\\pages\\Lessons.jsx", "source_location": "L1", "weight": 1.0}, {"source": "e_ailearningpath_ai_learning_frontend_frontend_src_pages_lessons_jsx", "target": "react_router_dom", "relation": "imports_from", "confidence": "EXTRACTED", "source_file": "E:\\AILearningPath\\ai-learning-frontend\\frontend\\src\\pages\\Lessons.jsx", "source_location": "L2", "weight": 1.0}, {"source": "e_ailearningpath_ai_learning_frontend_frontend_src_pages_lessons_jsx", "target": "e_ailearningpath_ai_learning_frontend_frontend_src_services_api", "relation": "imports_from", "confidence": "EXTRACTED", "source_file": "E:\\AILearningPath\\ai-learning-frontend\\frontend\\src\\pages\\Lessons.jsx", "source_location": "L3", "weight": 1.0}, {"source": "e_ailearningpath_ai_learning_frontend_frontend_src_pages_lessons_jsx", "target": "e_ailearningpath_ai_learning_frontend_frontend_src_store_authstore", "relation": "imports_from", "confidence": "EXTRACTED", "source_file": "E:\\AILearningPath\\ai-learning-frontend\\frontend\\src\\pages\\Lessons.jsx", "source_location": "L4", "weight": 1.0}, {"source": "e_ailearningpath_ai_learning_frontend_frontend_src_pages_lessons_jsx", "target": "e_ailearningpath_ai_learning_frontend_frontend_src_components_skeleton", "relation": "imports_from", "confidence": "EXTRACTED", "source_file": "E:\\AILearningPath\\ai-learning-frontend\\frontend\\src\\pages\\Lessons.jsx", "source_location": "L5", "weight": 1.0}, {"source": "e_ailearningpath_ai_learning_frontend_frontend_src_pages_lessons_jsx", "target": "lessons_ncertsubject", "relation": "contains", "confidence": "EXTRACTED", "source_file": "E:\\AILearningPath\\ai-learning-frontend\\frontend\\src\\pages\\Lessons.jsx", "source_location": "L23", "weight": 1.0}, {"source": "e_ailearningpath_ai_learning_frontend_frontend_src_pages_lessons_jsx", "target": "lessons_subjectbar", "relation": "contains", "confidence": "EXTRACTED", "source_file": "E:\\AILearningPath\\ai-learning-frontend\\frontend\\src\\pages\\Lessons.jsx", "source_location": "L26", "weight": 1.0}, {"source": "e_ailearningpath_ai_learning_frontend_frontend_src_pages_lessons_jsx", "target": "lessons_sciencesubbar", "relation": "contains", "confidence": "EXTRACTED", "source_file": "E:\\AILearningPath\\ai-learning-frontend\\frontend\\src\\pages\\Lessons.jsx", "source_location": "L47", "weight": 1.0}, {"source": "e_ailearningpath_ai_learning_frontend_frontend_src_pages_lessons_jsx", "target": "lessons_lessons", "relation": "contains", "confidence": "EXTRACTED", "source_file": "E:\\AILearningPath\\ai-learning-frontend\\frontend\\src\\pages\\Lessons.jsx", "source_location": "L128", "weight": 1.0}], "raw_calls": [{"caller_nid": "lessons_subjectbar", "callee": "map", "source_file": "E:\\AILearningPath\\ai-learning-frontend\\frontend\\src\\pages\\Lessons.jsx", "source_location": "L29"}, {"caller_nid": "lessons_sciencesubbar", "callee": "map", "source_file": "E:\\AILearningPath\\ai-learning-frontend\\frontend\\src\\pages\\Lessons.jsx", "source_location": "L50"}, {"caller_nid": "lessons_lessons", "callee": "useAuthStore", "source_file": "E:\\AILearningPath\\ai-learning-frontend\\frontend\\src\\pages\\Lessons.jsx", "source_location": "L129"}, {"caller_nid": "lessons_lessons", "callee": "useNavigate", "source_file": "E:\\AILearningPath\\ai-learning-frontend\\frontend\\src\\pages\\Lessons.jsx", "source_location": "L130"}, {"caller_nid": "lessons_lessons", "callee": "useCallback", "source_file": "E:\\AILearningPath\\ai-learning-frontend\\frontend\\src\\pages\\Lessons.jsx", "source_location": "L133"}, {"caller_nid": "lessons_lessons", "callee": "useCallback", "source_file": "E:\\AILearningPath\\ai-learning-frontend\\frontend\\src\\pages\\Lessons.jsx", "source_location": "L134"}, {"caller_nid": "lessons_lessons", "callee": "useCallback", "source_file": "E:\\AILearningPath\\ai-learning-frontend\\frontend\\src\\pages\\Lessons.jsx", "source_location": "L135"}, {"caller_nid": "lessons_lessons", "callee": "useState", "source_file": "E:\\AILearningPath\\ai-learning-frontend\\frontend\\src\\pages\\Lessons.jsx", "source_location": "L137"}, {"caller_nid": "lessons_lessons", "callee": "useState", "source_file": "E:\\AILearningPath\\ai-learning-frontend\\frontend\\src\\pages\\Lessons.jsx", "source_location": "L138"}, {"caller_nid": "lessons_lessons", "callee": "useState", "source_file": "E:\\AILearningPath\\ai-learning-frontend\\frontend\\src\\pages\\Lessons.jsx", "source_location": "L139"}, {"caller_nid": "lessons_lessons", "callee": "useState", "source_file": "E:\\AILearningPath\\ai-learning-frontend\\frontend\\src\\pages\\Lessons.jsx", "source_location": "L141"}, {"caller_nid": "lessons_lessons", "callee": "useState", "source_file": "E:\\AILearningPath\\ai-learning-frontend\\frontend\\src\\pages\\Lessons.jsx", "source_location": "L142"}, {"caller_nid": "lessons_lessons", "callee": "useState", "source_file": "E:\\AILearningPath\\ai-learning-frontend\\frontend\\src\\pages\\Lessons.jsx", "source_location": "L143"}, {"caller_nid": "lessons_lessons", "callee": "useState", "source_file": "E:\\AILearningPath\\ai-learning-frontend\\frontend\\src\\pages\\Lessons.jsx", "source_location": "L144"}, {"caller_nid": "lessons_lessons", "callee": "useState", "source_file": "E:\\AILearningPath\\ai-learning-frontend\\frontend\\src\\pages\\Lessons.jsx", "source_location": "L145"}, {"caller_nid": "lessons_lessons", "callee": "useEffect", "source_file": "E:\\AILearningPath\\ai-learning-frontend\\frontend\\src\\pages\\Lessons.jsx", "source_location": "L148"}, {"caller_nid": "lessons_lessons", "callee": "useEffect", "source_file": "E:\\AILearningPath\\ai-learning-frontend\\frontend\\src\\pages\\Lessons.jsx", "source_location": "L155"}, {"caller_nid": "lessons_lessons", "callee": "map", "source_file": "E:\\AILearningPath\\ai-learning-frontend\\frontend\\src\\pages\\Lessons.jsx", "source_location": "L171"}, {"caller_nid": "lessons_lessons", "callee": "filter", "source_file": "E:\\AILearningPath\\ai-learning-frontend\\frontend\\src\\pages\\Lessons.jsx", "source_location": "L175"}, {"caller_nid": "lessons_lessons", "callee": "filter", "source_file": "E:\\AILearningPath\\ai-learning-frontend\\frontend\\src\\pages\\Lessons.jsx", "source_location": "L179"}, {"caller_nid": "lessons_lessons", "callee": "find", "source_file": "E:\\AILearningPath\\ai-learning-frontend\\frontend\\src\\pages\\Lessons.jsx", "source_location": "L182"}, {"caller_nid": "lessons_lessons", "callee": "map", "source_file": "E:\\AILearningPath\\ai-learning-frontend\\frontend\\src\\pages\\Lessons.jsx", "source_location": "L202"}, {"caller_nid": "lessons_lessons", "callee": "map", "source_file": "E:\\AILearningPath\\ai-learning-frontend\\frontend\\src\\pages\\Lessons.jsx", "source_location": "L241"}, {"caller_nid": "lessons_lessons", "callee": "(() => {\n                const learnedInView = visibleLessons.filter((l) => completedTopics.has(l.topic));\n                if (learnedInView.length === 0) return null;\n                return (\n                  <div className=\"bg-apple-green/8 border border-apple-green/20 rounded-apple-lg p-4 flex items-center justify-between gap-4\">\n                    <div>\n                      <p className=\"text-[14px] font-semibold text-apple-green\">\n                        {learnedInView.length} topic{learnedInView.length > 1 ? \"s\" : \"\"} learned\n                      </p>\n                      <p className=\"text-[12px] text-apple-green/70 mt-0.5\">\n                        Practice only what you've studied so far\n                      </p>\n                    </div>\n                    <button\n                      onClick={() => navigate(\"/practice\", {\n                        state: { mixTopics: learnedInView.map((l) => l.topic), autoStart: true },\n                      })}\n                      className=\"shrink-0 px-4 py-2 rounded-apple text-[13px] font-semibold text-white transition-colors\"\n                      style={{ background: \"#34C759\" }}\n                    >\n                      Practice Learned \u2192\n                    </button>\n                  </div>\n                );\n              })", "source_file": "E:\\AILearningPath\\ai-learning-frontend\\frontend\\src\\pages\\Lessons.jsx", "source_location": "L259"}, {"caller_nid": "lessons_lessons", "callee": "map", "source_file": "E:\\AILearningPath\\ai-learning-frontend\\frontend\\src\\pages\\Lessons.jsx", "source_location": "L295"}, {"caller_nid": "lessons_lessons", "callee": "map", "source_file": "E:\\AILearningPath\\ai-learning-frontend\\frontend\\src\\pages\\Lessons.jsx", "source_location": "L321"}]}